mp3_combine_and_split/__init__.py
mp3_combine_and_split/cli.py
mp3_combine_and_split/lib.py
mp3_combine_and_split-0.0.7.dist-info/AUTHORS.rst
mp3_combine_and_split-0.0.7.dist-info/LICENSE
mp3_combine_and_split-0.0.7.dist-info/METADATA
mp3_combine_and_split-0.0.7.dist-info/WHEEL
mp3_combine_and_split-0.0.7.dist-info/entry_points.txt
mp3_combine_and_split-0.0.7.dist-info/top_level.txt
mp3_combine_and_split-0.0.7.dist-info/RECORD
