Metadata-Version: 2.1
Name: mp3-combine-and-split
Version: 0.0.7
Summary: Utility to Combine MP3 and then split based on a defined max play time. 
Home-page: https://github.com/philroche/mp3_combine_and_split
Author: Philip Roche
Author-email: phil@philroche.net
License: GNU General Public License v3
Keywords: mp3_combine_and_split
Platform: UNKNOWN
Classifier: Development Status :: 2 - Pre-Alpha
Classifier: Intended Audience :: Developers
Classifier: License :: OSI Approved :: GNU General Public License v3 (GPLv3)
Classifier: Natural Language :: English
Classifier: Programming Language :: Python :: 3
Classifier: Programming Language :: Python :: 3.5
Classifier: Programming Language :: Python :: 3.6
Classifier: Programming Language :: Python :: 3.7
Classifier: Programming Language :: Python :: 3.8
Requires-Python: >=3.5
Requires-Dist: Click (>=7.0)
Requires-Dist: pydub
Requires-Dist: eyed3
Requires-Dist: natsort
Requires-Dist: python-slugify
